{
  "report_date": "2026-06-11",
  "overall_sentiment": "持平",
  "overall_summary": "台灣房市在政策管制下，預售與成屋市場呈現分歧，部分地區房價仍具支撐，但整體交易量能趨緩，購屋負擔壓力仍高。",
  "presale_market": {
    "sentiment": "持平",
    "note": "新聞未直接提及預售屋市場熱絡程度，但土增稅與房地合一稅減少顯示整體交易量能趨緩，可能影響預售屋市場。"
  },
  "resale_market": {
    "sentiment": "冷清",
    "note": "前5月土地增值稅年減8.9%，個人房地合一稅年減7.6%，顯示房地交易量減少，大額稅款案件減少，反映成屋及中古屋市場交易動能放緩。"
  },
  "policy": [
    {
      "title": "高房價議題",
      "impact": "銀行公會理事長董瑞斌提出地上權住宅作為高房價下的購屋選項，暗示政府與金融界正思考解決高房價問題，可能推動更多元化的購屋方案以減輕買方負擔。"
    }
  ],
  "regions": [
    {
      "county": "新竹市",
      "sentiment": "熱絡",
      "heat_score": 75,
      "note": "漢唐、辛耘、中華立鼎、凌嘉科技等半導體相關產業接單暢旺，有助於產業人才聚集與就業機會，支撐當地房市需求，儘管成屋均價較去年微幅下跌，但長期仍呈上漲趨勢。"
    },
    {
      "county": "臺南市",
      "sentiment": "熱絡",
      "heat_score": 70,
      "note": "立凱電規劃在南台灣建置LFP前驅體新產線，預計2027年開始出貨，可能為南台灣帶來新的就業機會，對當地房市有潛在支撐。"
    }
  ],
  "ai_summary": {
    "future_trend": "短期內，股市熱絡和產業投資（如半導體）可能帶來資金動能，支撐特定區域房價。然而，長期來看，台灣人口負成長與少子化將縮減自住需求，加上高房價造成的購屋負擔壓力，以及政策可能持續關注高房價議題，這些結構性因素可能對房市形成長期壓力。研判趨勢將以長期人口與供給結構為主要考量。",
    "structural_factors": [
      "人口負成長與少子化使長期自住需求縮減，影響未來房市支撐力。",
      "餘屋與新增供給量若持續增加，可能導致部分區域供過於求。",
      "房價所得比偏高，購屋負擔吃緊，限制了潛在買方的購屋能力。",
      "美國升息疑慮可能影響未來房貸利率走勢，增加購屋成本。"
    ],
    "policy_shift": "目前政策傾向持續關注高房價問題，雖然新聞未直接提及新的打炒房措施，但銀行公會提出地上權住宅的討論，顯示政府與相關單位正思考多元化方案以因應高房價，未來可能朝向提供更多元的居住選擇或稅負調整方向發展。",
    "buyer_impact": "中性",
    "buyer_advice": "面對當前房市，買方應特別留意各地區產業發展與人口結構的差異，如新竹市、臺南市等有大型產業投資的區域，短期內房價可能相對有支撐。同時，應審慎評估自身負擔能力，並可關注如地上權住宅等新興購屋選項。對於人口外流或供給量大的區域，長期保值風險較高，需謹慎評估。",
    "regulations": [],
    "overview": "整體而言，台灣房市短期內受資金與特定產業利多支撐，但交易量能已顯疲態。長期而言，人口結構變化與高房價負擔仍是主要挑戰，買方應權衡短期動能與長期風險，做出謹慎決策。"
  },
  "evidence_news": [
    {
      "title": "薪資難追物價漲幅 80%馬來西亞人成「月光族」",
      "source": "中央社 財經",
      "url": "https://www.cna.com.tw/news/aopl/202606110309.aspx"
    },
    {
      "title": "財部：大額稅款案件減少 前5月土增稅年減8.9%",
      "source": "中央社 財經",
      "url": "https://www.cna.com.tw/news/afe/202606110287.aspx"
    },
    {
      "title": "5月證交稅年增2.9倍 實徵704億元續創單月新高",
      "source": "中央社 財經",
      "url": "https://www.cna.com.tw/news/afe/202606110284.aspx"
    },
    {
      "title": "伊朗局勢與升息疑慮拖累 亞股普遍收跌",
      "source": "中央社 財經",
      "url": "https://www.cna.com.tw/news/afe/202606110282.aspx"
    },
    {
      "title": "漢唐在手訂單1939億 辛耘訂單展望達2028年",
      "source": "中央社 財經",
      "url": "https://www.cna.com.tw/news/afe/202606110279.aspx"
    },
    {
      "title": "凌嘉科擬6/15登錄興櫃 前4月每股純益0.51元",
      "source": "中央社 財經",
      "url": "https://www.cna.com.tw/news/afe/202606110266.aspx"
    },
    {
      "title": "5月全體上市公司總營收4.88兆元 年增34%",
      "source": "中央社 財經",
      "url": "https://www.cna.com.tw/news/afe/202606110259.aspx"
    },
    {
      "title": "全新通過6億元內購置土地 啟動新廠計畫",
      "source": "中央社 財經",
      "url": "https://www.cna.com.tw/news/afe/202606110255.aspx"
    },
    {
      "title": "半導體先進製造封裝投資穩 全球首季設備銷售額創高",
      "source": "中央社 財經",
      "url": "https://www.cna.com.tw/news/afe/202606110253.aspx"
    },
    {
      "title": "中國臨時取消與歐盟高層會議 北京稱雙方仍保持溝通",
      "source": "中央社 財經",
      "url": "https://www.cna.com.tw/news/acn/202606110239.aspx"
    },
    {
      "title": "5月總稅收5770億元 證交稅大增2.9倍連10紅",
      "source": "中央社 財經",
      "url": "https://www.cna.com.tw/news/afe/202606110232.aspx"
    },
    {
      "title": "立凱電打進特斯拉供應鏈 2.8億元現增過關籌資建廠",
      "source": "中央社 財經",
      "url": "https://www.cna.com.tw/news/afe/202606110231.aspx"
    },
    {
      "title": "新台幣升3.7分 收31.631元",
      "source": "中央社 財經",
      "url": "https://www.cna.com.tw/news/afe/202606110229.aspx"
    },
    {
      "title": "水利署估全台水庫進帳3.9億噸 曾文烏山頭蓄水率達2成",
      "source": "中央社 財經",
      "url": "https://www.cna.com.tw/news/afe/202606110227.aspx"
    },
    {
      "title": "順達通過配息11.5元 下半年業績優於上半年",
      "source": "中央社 財經",
      "url": "https://www.cna.com.tw/news/afe/202606110218.aspx"
    },
    {
      "title": "房價高漲 銀行公會董瑞斌：思考地上權住宅當退休宅",
      "source": "中央社 財經",
      "url": "https://www.cna.com.tw/news/afe/202606110216.aspx"
    },
    {
      "title": "中華電小金雞中華立鼎6/17登興櫃 前4月每股賺7.07元",
      "source": "中央社 財經",
      "url": "https://www.cna.com.tw/news/afe/202606110215.aspx"
    },
    {
      "title": "三大法人賣超台股353.91億元",
      "source": "中央社 財經",
      "url": "https://www.cna.com.tw/news/afe/202606110204.aspx"
    }
  ],
  "raw_news": [
    {
      "title": "薪資難追物價漲幅 80%馬來西亞人成「月光族」",
      "source": "中央社 財經",
      "url": "https://www.cna.com.tw/news/aopl/202606110309.aspx",
      "summary": "（中央社記者黃自強吉隆坡11日專電）白天上班、下班駕駛Grab，或週末兼差接案，成為許多馬來西亞家庭的生活寫照。當地學者指出，隨著生活成本攀升，約80%大馬人屬於「月光族」，收入幾乎全數用於日常開支，單靠一份薪資已難追上物價漲幅。",
      "published": "2026-06-11T10:17:19+00:00",
      "origin": "中央社 財經"
    },
    {
      "title": "財部：大額稅款案件減少 前5月土增稅年減8.9%",
      "source": "中央社 財經",
      "url": "https://www.cna.com.tw/news/afe/202606110287.aspx",
      "summary": "（中央社記者呂晏慈台北11日電）財政部今天公布全國賦稅收入統計，前5月房市相關稅目仍呈現增減互見，契稅年增6.9%，個人房地合一稅年減7.6%，另受到房地交易量及大額稅款案件減少影響，土地增值稅年減8.9%。",
      "published": "2026-06-11T09:50:32+00:00",
      "origin": "中央社 財經"
    },
    {
      "title": "5月證交稅年增2.9倍 實徵704億元續創單月新高",
      "source": "中央社 財經",
      "url": "https://www.cna.com.tw/news/afe/202606110284.aspx",
      "summary": "（中央社記者呂晏慈台北11日電）財政部今天公布5月全國賦稅收入初步統計，受惠台股漲勢延續，帶動單月證交稅實徵淨額704億元，再度刷新單月新高紀錄，年增2.9倍，漲幅為逾22年以來新高；累計前5月證交稅實徵淨額2487億元，亦為同期新高。",
      "published": "2026-06-11T09:44:26+00:00",
      "origin": "中央社 財經"
    },
    {
      "title": "伊朗局勢與升息疑慮拖累 亞股普遍收跌",
      "source": "中央社 財經",
      "url": "https://www.cna.com.tw/news/afe/202606110282.aspx",
      "summary": "（中央社香港11日綜合外電報導）受到伊朗局勢疑慮再起，加上美國升息前景等負面因素影響，亞洲股市今天普遍收跌。",
      "published": "2026-06-11T09:40:22+00:00",
      "origin": "中央社 財經"
    },
    {
      "title": "漢唐在手訂單1939億 辛耘訂單展望達2028年",
      "source": "中央社 財經",
      "url": "https://www.cna.com.tw/news/afe/202606110279.aspx",
      "summary": "（中央社記者張建中新竹11日電）無塵室廠漢唐與半導體設備廠辛耘接單暢旺，其中，漢唐在手訂單金額高達新台幣1939.37億元。辛耘部分訂單展望已達2028年。",
      "published": "2026-06-11T09:38:15+00:00",
      "origin": "中央社 財經"
    },
    {
      "title": "凌嘉科擬6/15登錄興櫃 前4月每股純益0.51元",
      "source": "中央社 財經",
      "url": "https://www.cna.com.tw/news/afe/202606110266.aspx",
      "summary": "（中央社記者張建中台北11日電）半導體設備廠凌嘉科技預計6月15日以每股130元參考價登錄興櫃，今年累計前4月營收新台幣3.14億元，稅後淨利4231萬元，每股純益0.51元。",
      "published": "2026-06-11T09:19:48+00:00",
      "origin": "中央社 財經"
    },
    {
      "title": "5月全體上市公司總營收4.88兆元 年增34%",
      "source": "中央社 財經",
      "url": "https://www.cna.com.tw/news/afe/202606110259.aspx",
      "summary": "（中央社記者曾仁凱台北11日電）台灣證券交易所今天公告，除金融保險業與三商投控，其餘1047家上市公司已於6月10日前完成5月營收申報作業。上述全體上市公司5月營收總計新台幣4兆8806億元，較去年同期大幅成長34.12%。其中，營收成長公司691家，衰退公司356家。",
      "published": "2026-06-11T09:07:31+00:00",
      "origin": "中央社 財經"
    },
    {
      "title": "全新通過6億元內購置土地 啟動新廠計畫",
      "source": "中央社 財經",
      "url": "https://www.cna.com.tw/news/afe/202606110255.aspx",
      "summary": "（中央社記者曾仁凱台北11日電）砷化鎵（GaAs）上游磊晶廠全新今天公告，為配合長期發展策略及營運需求，擬購置土地作為建置廠房使用。全新董事會今天決議授權董事長，於不超過新台幣6億元額度內，全權處理土地購置相關事宜。",
      "published": "2026-06-11T09:03:22+00:00",
      "origin": "中央社 財經"
    },
    {
      "title": "半導體先進製造封裝投資穩 全球首季設備銷售額創高",
      "source": "中央社 財經",
      "url": "https://www.cna.com.tw/news/afe/202606110253.aspx",
      "summary": "（中央社記者張建中新竹11日電）國際半導體產業協會（SEMI）統計，2026年第1季全球半導體製造設備銷售額達365.5億美元，創下單季歷史新高，季增1%，較去年同期增加14%。",
      "published": "2026-06-11T08:58:18+00:00",
      "origin": "中央社 財經"
    },
    {
      "title": "中國臨時取消與歐盟高層會議 北京稱雙方仍保持溝通",
      "source": "中央社 財經",
      "url": "https://www.cna.com.tw/news/acn/202606110239.aspx",
      "summary": "（中央社記者張淑伶北京11日電）中國與歐洲貿易摩擦升溫，外媒報導中方突然取消本月在北京與歐盟高層的會晤。中國外交部發言人林劍今天說，中歐雙方就相關對話保持著溝通。",
      "published": "2026-06-11T08:33:48+00:00",
      "origin": "中央社 財經"
    },
    {
      "title": "5月總稅收5770億元 證交稅大增2.9倍連10紅",
      "source": "中央社 財經",
      "url": "https://www.cna.com.tw/news/afe/202606110232.aspx",
      "summary": "（中央社記者呂晏慈台北11日電）財政部今天公布5月全國賦稅收入新台幣5770億元、年增84%；代表股市交易動能的證券交易稅5月實徵704億元、年增2.9倍，反映股市交易熱絡，已是連續10個月正成長。",
      "published": "2026-06-11T08:09:33+00:00",
      "origin": "中央社 財經"
    },
    {
      "title": "立凱電打進特斯拉供應鏈 2.8億元現增過關籌資建廠",
      "source": "中央社 財經",
      "url": "https://www.cna.com.tw/news/afe/202606110231.aspx",
      "summary": "（中央社記者曾仁凱台北11日電）鋰鐵電池正極材料廠立凱電打進特斯拉（Tesla）供應鏈，新台幣2.8億元的現金增資案本週獲准通過，立凱電規劃斥資逾3億元在南台灣建置LFP（磷酸鋰鐵）前驅體5萬噸新產線，預計2027年開始出貨。",
      "published": "2026-06-11T08:08:31+00:00",
      "origin": "中央社 財經"
    },
    {
      "title": "新台幣升3.7分 收31.631元",
      "source": "中央社 財經",
      "url": "https://www.cna.com.tw/news/afe/202606110229.aspx",
      "summary": "（中央社台北11日電）台北外匯市場新台幣兌美元今天收盤收31.631元，升3.7分，成交金額20.01億美元。",
      "published": "2026-06-11T08:06:26+00:00",
      "origin": "中央社 財經"
    },
    {
      "title": "水利署估全台水庫進帳3.9億噸 曾文烏山頭蓄水率達2成",
      "source": "中央社 財經",
      "url": "https://www.cna.com.tw/news/afe/202606110227.aspx",
      "summary": "（中央社記者謝怡璇台北11日電）水利署表示，截至今天上午7時止，預估本波降雨為全台水庫帶來3.9億噸水；曾文及烏山頭水庫蓄水量提升至1億380萬噸，蓄水率達到2成。由於部分降雨逕流尚未完全匯入庫區，預估蓄水量仍有回升空間。",
      "published": "2026-06-11T08:03:22+00:00",
      "origin": "中央社 財經"
    },
    {
      "title": "順達通過配息11.5元 下半年業績優於上半年",
      "source": "中央社 財經",
      "url": "https://www.cna.com.tw/news/afe/202606110218.aspx",
      "summary": "（中央社記者曾仁凱台北11日電）鋰電池模組廠順達今天召開股東常會，董事長鍾聰明表示，BBU（電池備援電力模組）需求持續放大，順達積極擴充新產能；隨著產能年底開出，順達看好今年下半年業績會比上半年好很多，且明年會比今年好。",
      "published": "2026-06-11T07:46:03+00:00",
      "origin": "中央社 財經"
    },
    {
      "title": "房價高漲 銀行公會董瑞斌：思考地上權住宅當退休宅",
      "source": "中央社 財經",
      "url": "https://www.cna.com.tw/news/afe/202606110216.aspx",
      "summary": "（中央社記者呂晏慈台北11日電）銀行公會今天表示，高房價下，不需負擔土地取得成本的地上權住宅，提供了民眾達成購屋夢想的另種可能性。銀行公會理事長董瑞斌指出，不只年輕人買不起房，年紀大的也買不起，他在思考是否可以地上權住宅作為退休宅，當高房價下的選項。",
      "published": "2026-06-11T07:43:59+00:00",
      "origin": "中央社 財經"
    },
    {
      "title": "中華電小金雞中華立鼎6/17登興櫃 前4月每股賺7.07元",
      "source": "中央社 財經",
      "url": "https://www.cna.com.tw/news/afe/202606110215.aspx",
      "summary": "（中央社記者張建中新竹11日電）中華電信轉投資持股62%的感測器廠中華立鼎，預計6月17日以每股參考價120元登錄興櫃，今年累計前4月營收達新台幣2.01億元，稅後淨利8035萬元，每股純益7.07元。",
      "published": "2026-06-11T07:42:57+00:00",
      "origin": "中央社 財經"
    },
    {
      "title": "三大法人賣超台股353.91億元",
      "source": "中央社 財經",
      "url": "https://www.cna.com.tw/news/afe/202606110204.aspx",
      "summary": "（中央社台北11日電）台股今天跌76.08點，收在43149.46點，成交值新台幣1兆2579.75億元。三大法人外資及陸資賣超、投信買超、自營商賣超，合計賣超353.91億元。",
      "published": "2026-06-11T07:07:33+00:00",
      "origin": "中央社 財經"
    }
  ]
}