{
  "report_date": "2026-06-28",
  "overall_sentiment": "熱絡",
  "overall_summary": "台灣房市受半導體與AI產業帶動的科技人才需求支撐，部分區域房價仍維持高檔，儘管國際油價調降，但整體經濟活動仍活絡。",
  "presale_market": {
    "sentiment": "熱絡",
    "note": "新聞雖未直接提及預售屋市場，但半導體產業的強勁發展與人才需求，預期將帶動相關區域的房市需求，尤其預售屋市場更容易受未來預期心理影響。"
  },
  "resale_market": {
    "sentiment": "熱絡",
    "note": "新聞雖未直接提及成屋/中古屋市場，但台積電等半導體產業的蓬勃發展，以及台灣在AI領域的關鍵地位，將吸引更多人才湧入，進而推升成屋市場的需求與價格。從歷年數據看，多數縣市成屋均價仍在成長。"
  },
  "policy": [],
  "regions": [
    {
      "county": "雲林縣",
      "sentiment": "冷清",
      "heat_score": 30,
      "note": "雲林縣因豪雨造成葉菜類災損逾7成，恐衝擊農民生計，間接影響地方經濟與房市氛圍。"
    },
    {
      "county": "新竹市",
      "sentiment": "熱絡",
      "heat_score": 85,
      "note": "世界先進新加坡廠良率高並發放高額獎金，顯示半導體產業景氣良好，對新竹科學園區所在地的新竹市及周邊區域房市形成支撐。"
    },
    {
      "county": "高雄市",
      "sentiment": "熱絡",
      "heat_score": 75,
      "note": "亞洲資產管理中心高雄專區的推動，以及金融業搶才大戰，顯示高雄的金融與人才需求旺盛，對當地房市有正面影響。"
    }
  ],
  "ai_summary": {
    "future_trend": "短期房市受惠於台灣在全球AI供應鏈的關鍵地位，半導體產業的強勁需求與人才磁吸效應，資金動能充沛，預期部分科技重鎮區域房價仍有支撐。然而，長期而言，台灣人口持續負成長與少子化趨勢，加上部分區域可能面臨餘屋供給過剩問題，將對自住需求構成結構性壓力。因此，未來房市趨勢研判將主要建立在短期資金動能與產業發展的支撐上，但長期結構性風險不容忽視。",
    "structural_factors": [
      "人口負成長與少子化使長期自住需求縮減",
      "餘屋/新增供給與待售存量可能在部分區域增加",
      "房價所得比偏高，購屋負擔能力持續吃緊",
      "國際半導體與AI產業鏈對台灣經濟及人才的持續吸納"
    ],
    "policy_shift": "本次新聞未提及新的房市政策或信用管制措施，顯示政府目前可能維持既有打炒房政策，並無明顯趨嚴或鬆綁的轉變。",
    "buyer_impact": "中性",
    "buyer_advice": "欲購屋者應密切關注產業發展帶動的區域性需求，尤其是有大型科技產業進駐或擴張的縣市，其房價支撐力道較強。同時，也要留意人口外流或供給量大的區域，長期保值性可能面臨挑戰。建議購屋前務必考量自身負擔能力，並審慎評估長期持有風險。",
    "regulations": [
      "平均地權條例",
      "囤房稅2.0",
      "央行選擇性信用管制",
      "新青安房貸"
    ],
    "overview": "整體而言，台灣房市短期內受科技產業活絡與人才需求帶動，呈現局部熱絡態勢。然而，購屋者仍需謹慎評估長期人口結構變遷與區域供給量，以應對潛在的結構性風險。"
  },
  "evidence_news": [
    {
      "title": "先進封裝成AI競爭關鍵 紐時：美國依賴台積電更甚以往",
      "source": "中央社 財經",
      "url": "https://www.cna.com.tw/news/aopl/202606270165.aspx"
    },
    {
      "title": "台灣半導體攬才吸睛 馬來西亞掀赴台就業熱潮",
      "source": "中央社 財經",
      "url": "https://www.cna.com.tw/news/afe/202606270147.aspx"
    },
    {
      "title": "雲林葉菜類災損逾7成 恐衝擊市場蔬菜供應",
      "source": "中央社 財經",
      "url": "https://www.cna.com.tw/news/afe/202606270131.aspx"
    },
    {
      "title": "中油宣布 29日起汽油調降1元、柴油降0.8元",
      "source": "中央社 財經",
      "url": "https://www.cna.com.tw/news/ahel/202606270114.aspx"
    },
    {
      "title": "亞資中心藍圖下的人才戰 學者：攬才須靠3引擎",
      "source": "中央社 財經",
      "url": "https://www.cna.com.tw/news/afe/202606270088.aspx"
    },
    {
      "title": "跳脫銷售員框架 星展銀鼓勵跨國跨單位輪調黏住人才",
      "source": "中央社 財經",
      "url": "https://www.cna.com.tw/news/afe/202606270087.aspx"
    },
    {
      "title": "外商銀搶才大戰 滙豐銀職涯路徑與培訓一次看懂",
      "source": "中央社 財經",
      "url": "https://www.cna.com.tw/news/afe/202606270086.aspx"
    },
    {
      "title": "世界先進新加坡廠首批良率逾99% 發逾1億元獎金",
      "source": "中央社 財經",
      "url": "https://www.cna.com.tw/news/afe/202606270048.aspx"
    }
  ],
  "raw_news": [
    {
      "title": "今彩539第115156期 頭獎1注中獎",
      "source": "中央社 財經",
      "url": "https://www.cna.com.tw/news/ahel/202606270206.aspx",
      "summary": "（中央社台北27日電）今彩539第115156期開獎，中獎號碼32、04、31、14、21；派彩結果，頭獎1注中獎，獎金新台幣800萬元。",
      "published": "2026-06-27T14:08:40+00:00",
      "origin": "中央社 財經"
    },
    {
      "title": "今彩539第115156期開獎",
      "source": "中央社 財經",
      "url": "https://www.cna.com.tw/news/ahel/202606270194.aspx",
      "summary": "（中央社台北27日電）今彩539第115156期開獎，中獎號碼32、04、31、14、21。3星彩中獎號碼374，4星彩中獎號碼5097。",
      "published": "2026-06-27T12:42:09+00:00",
      "origin": "中央社 財經"
    },
    {
      "title": "先進封裝成AI競爭關鍵 紐時：美國依賴台積電更甚以往",
      "source": "中央社 財經",
      "url": "https://www.cna.com.tw/news/aopl/202606270165.aspx",
      "summary": "（中央社紐約26日綜合外電報導）先進晶片封裝技術大幅提升人工智慧（AI）運算效能，也讓美國對台灣依賴程度更甚以往。「紐約時報」報導，這是全球AI主導權之爭關鍵瓶頸，先進晶片封裝幾乎全部由台積電包辦。",
      "published": "2026-06-27T09:40:03+00:00",
      "origin": "中央社 財經"
    },
    {
      "title": "台灣半導體攬才吸睛 馬來西亞掀赴台就業熱潮",
      "source": "中央社 財經",
      "url": "https://www.cna.com.tw/news/afe/202606270147.aspx",
      "summary": "（中央社記者黃自強吉隆坡27日專電）AI浪潮席捲全球，科技人才需求升溫。2026年馬來西亞國家職涯博覽會登場，台灣也組團攬才，其中，半導體相關業者提供涵蓋晶片設計、封裝測試等領域職缺最受青睞。不少大馬青年更將赴台發展列優先選項。",
      "published": "2026-06-27T09:15:23+00:00",
      "origin": "中央社 財經"
    },
    {
      "title": "雲林葉菜類災損逾7成 恐衝擊市場蔬菜供應",
      "source": "中央社 財經",
      "url": "https://www.cna.com.tw/news/afe/202606270131.aspx",
      "summary": "（中央社記者黃國芳雲林縣27日電）受鋒面及西南風影響，雲林縣昨晚起出現局部豪雨或大豪雨，造成二崙等地葉菜類受災嚴重。縣長張麗善今天勘災後表示，損失逾7成，不僅影響菜農生計，恐衝擊後續市場蔬菜供應。",
      "published": "2026-06-27T07:56:47+00:00",
      "origin": "中央社 財經"
    },
    {
      "title": "中油宣布 29日起汽油調降1元、柴油降0.8元",
      "source": "中央社 財經",
      "url": "https://www.cna.com.tw/news/ahel/202606270114.aspx",
      "summary": "（中央社記者呂晏慈台北27日電）美伊啟動協商，荷莫茲海峽通航量逐步回升，國際油價下跌。台灣中油公司今天宣布，自29日凌晨零時起至7月5日晚上12時止，汽、柴油各調降新台幣1元及0.8元",
      "published": "2026-06-27T06:11:10+00:00",
      "origin": "中央社 財經"
    },
    {
      "title": "SpaceX將納入那斯達克100指數 帶動被動資金流入",
      "source": "中央社 財經",
      "url": "https://www.cna.com.tw/news/afe/202606270110.aspx",
      "summary": "（中央社華盛頓26日綜合外電報導）那斯達克交易所（Nasdaq）今天證實，SpaceX將於7月7日被納入以科技股為主的那斯達克100指數，為馬斯克（Elon Musk）旗下火箭及人工智慧（AI）巨擘，鋪平被動投資資金湧入的道路。",
      "published": "2026-06-27T05:59:01+00:00",
      "origin": "中央社 財經"
    },
    {
      "title": "經部：縣市排水治理率增至45% 持續推動系統性治水",
      "source": "中央社 財經",
      "url": "https://www.cna.com.tw/news/afe/202606270094.aspx",
      "summary": "（中央社記者呂晏慈台北27日電）經濟部今天說，目前縣市管河川及區域排水治理率已由19%提高到45%，許多地區治水已展現成效。治水沒有捷徑，中央將持續編列治水預算，給予地方必要協助，讓治水工程發揮最大效益，達到「最小淹水面積、最短退水時間、最高安全標準」目標。",
      "published": "2026-06-27T04:53:24+00:00",
      "origin": "中央社 財經"
    },
    {
      "title": "亞資中心藍圖下的人才戰 學者：攬才須靠3引擎",
      "source": "中央社 財經",
      "url": "https://www.cna.com.tw/news/afe/202606270088.aspx",
      "summary": "亞資中心高雄專區週年（中央社記者呂晏慈台北27日電）台灣迎向亞洲資產管理中心目標，不只是宣告金融開放，更是一場人才競賽。隨著金融創新、跨境理財與財富管理業務加速發展，加上科技業高薪磁吸效應，帶動金融業搶才大戰全面升級。學者建議，業者須提升薪資待遇與培訓機制，政府則要提供吸引海外人才的租稅獎勵與配套，透過薪酬、員工培訓與租稅形成3大攬才利器。",
      "published": "2026-06-27T04:26:11+00:00",
      "origin": "中央社 財經"
    },
    {
      "title": "跳脫銷售員框架 星展銀鼓勵跨國跨單位輪調黏住人才",
      "source": "中央社 財經",
      "url": "https://www.cna.com.tw/news/afe/202606270087.aspx",
      "summary": "亞資中心高雄專區週年（中央社記者呂晏慈台北27日電）政府推動台灣成為亞洲資產管理中心，透過高雄專區已成功邁開步伐，然而人才仍是首要挑戰。成立逾50年，新加坡最大商業銀行星展銀行深耕資產管理服務，談及人才培育經驗時表示，除了投入資源培養員工在品酒、產業等有助於與高資產客戶互動的專業素養外，也透過鼓勵輪調的企業文化，提升員工職涯發展空間，成功留住資產管理人才。",
      "published": "2026-06-27T04:26:09+00:00",
      "origin": "中央社 財經"
    },
    {
      "title": "外商銀搶才大戰 滙豐銀職涯路徑與培訓一次看懂",
      "source": "中央社 財經",
      "url": "https://www.cna.com.tw/news/afe/202606270086.aspx",
      "summary": "亞資中心高雄專區週年（中央社記者呂晏慈台北27日電）看好台灣高資產財富管理市場，指標外商銀行滙豐銀行今年公布在台財管策略，其中「強化人才」、「擴大理專團隊」成為不容忽視的關鍵字。滙豐（台灣）商業銀行國際財富管理暨卓越理財事業處負責人胡醒賢直言，隨著市場做大，人才需求缺口隨之擴大，各機構必須開出更有競爭力條件來吸引更優秀的人才。",
      "published": "2026-06-27T04:26:07+00:00",
      "origin": "中央社 財經"
    },
    {
      "title": "華盛頓首航 長榮航：爭取波音加速交機、拚天天有班",
      "source": "中央社 財經",
      "url": "https://www.cna.com.tw/news/afe/202606270080.aspx",
      "summary": "（中央社記者江明晏華盛頓26日電）長榮航空今天在華盛頓舉辦開航晚宴，總經理孫嘉明表示，目前桃園直飛華盛頓每週雖然只有4班，正全力向美國波音公司爭取盡快交機，盼明年某個時候，桃園飛往華盛頓特區的航班頻率，可增加到「天天有班」，也就是每週7班。",
      "published": "2026-06-27T04:09:54+00:00",
      "origin": "中央社 財經"
    },
    {
      "title": "世界先進新加坡廠首批良率逾99% 發逾1億元獎金",
      "source": "中央社 財經",
      "url": "https://www.cna.com.tw/news/afe/202606270048.aspx",
      "summary": "（中央社記者張建中新竹27日電）世界先進今天舉辦家庭日活動，董事長方略表示，今年8吋晶圓代工供不應求，後續需求依然維持穩健，新加坡廠今年6月初產出第1批40奈米晶片，良率超過99%，管理階層決定發放超過新台幣1億元獎金給基層員工。",
      "published": "2026-06-27T02:48:45+00:00",
      "origin": "中央社 財經"
    },
    {
      "title": "關貿網路連9年配息創高 現金股利3.55元股東會通過",
      "source": "中央社 財經",
      "url": "https://www.cna.com.tw/news/afe/202606270040.aspx",
      "summary": "（中央社記者呂晏慈台北27日電）關貿網路股東常會通過每股配發現金股利新台幣3.55元，連續9年創新高。董事長張陸生說明，因應新興資訊科技的快速演進，將加速人工智慧（AI）落地，讓創新科技真正轉化為數據價值，成為永續成長的核心引擎。",
      "published": "2026-06-27T02:20:28+00:00",
      "origin": "中央社 財經"
    },
    {
      "title": "經部赴德招商 爭取國際供應鏈關鍵廠商投資台灣",
      "source": "中央社 財經",
      "url": "https://www.cna.com.tw/news/afe/202606270032.aspx",
      "summary": "（中央社記者呂晏慈台北27日電）為吸引國際關鍵技術領導廠商擴大在台投資，經濟部6月赴德招商，拜會蔡司（ZEISS）、德芯科技（PVA TePla）等指標廠商，促成德商在半導體先進材料、在地研發及快速驗證等領域後續對話，並強化德商在台投資規劃，攜手補強台灣半導體生態系在關鍵材料及設備的缺口。",
      "published": "2026-06-27T01:29:10+00:00",
      "origin": "中央社 財經"
    },
    {
      "title": "豪雨釀災 產險公會：保戶可依颱風洪水保險申請理賠",
      "source": "中央社 財經",
      "url": "https://www.cna.com.tw/news/ahel/202606270026.aspx",
      "summary": "（中央社記者呂晏慈台北27日電）受颱風外圍環流與西南風影響，全台連日豪雨多地傳出災情。產險公會表示，若因颱風或洪水造成財物損失，保戶可逕向承保公司依「颱風洪水補償費用」條款約定申請理賠。",
      "published": "2026-06-27T00:56:57+00:00",
      "origin": "中央社 財經"
    },
    {
      "title": "ICGN執行長讚台灣擴大參與：優秀應讓全世界知道【專訪】",
      "source": "中央社 財經",
      "url": "https://www.cna.com.tw/news/afe/202606270022.aspx",
      "summary": "（中央社記者黃雅詩阿姆斯特丹26日專電）成員涵蓋全球知名投資機構的國際公司治理協會（ICGN）在荷蘭舉行年會，執行長席森表示，今年台灣團陣容壯盛，集保、櫃買兩位重要機構董事長親自率團出席意義重大，「因為台灣有許多令人興奮的優秀作法，必須讓全世界知道」。",
      "published": "2026-06-27T00:36:48+00:00",
      "origin": "中央社 財經"
    },
    {
      "title": "韓國瑜訪美團搭華盛頓首航返台 讚台美里程碑",
      "source": "中央社 財經",
      "url": "https://www.cna.com.tw/news/afe/202606270020.aspx",
      "summary": "（中央社記者江明晏華盛頓26日電）立法院長韓國瑜與跨黨派立委結束訪美行程，今天搭乘長榮航空從華盛頓直飛桃園的首航班機返台。韓國瑜表示，新航線開通是台美關係發展里程碑。台美地理距離有1/3個地球遙遠，但雙方在民主、自由、法治的價值連結緊密。",
      "published": "2026-06-27T00:33:44+00:00",
      "origin": "中央社 財經"
    }
  ]
}